{
    "accel_to_decel_enable": "1",
    "bottom_shell_layers": "5",
    "bottom_shell_thickness": "1",
    "bridge_acceleration": "1500",
    "bridge_angle": "45",
    "bridge_speed": "30",
    "brim_type": "no_brim",
    "default_acceleration": "8000",
    "elefant_foot_compensation": "0.2",
    "enable_prime_tower": "0",
    "ensure_vertical_shell_thickness": "0",
    "from": "User",
    "gap_infill_speed": "80",
    "infill_direction": "0",
    "inherits": "0.20mm Standard @Snapmaker",
    "initial_layer_acceleration": "8000",
    "initial_layer_infill_speed": "120",
    "initial_layer_line_width": "0.45",
    "initial_layer_speed": "80",
    "initial_layer_travel_speed": "520",
    "inner_wall_acceleration": "8000",
    "inner_wall_speed": "150",
    "internal_bridge_support_thickness": "0.6",
    "internal_solid_infill_acceleration": "10000",
    "internal_solid_infill_line_width": "0.45",
    "internal_solid_infill_speed": "200",
    "is_custom_defined": "0",
    "minimum_sparse_infill_area": "30",
    "name": "0.4mm-0.2mm TPU PSM-01_V2.4-350",
    "only_one_wall_first_layer": "1",
    "only_one_wall_top": "1",
    "outer_wall_acceleration": "3000",
    "outer_wall_speed": "100",
    "overhang_2_4_speed": "40",
    "overhang_3_4_speed": "20",
    "precise_outer_wall": "1",
    "print_settings_id": "0.4mm-0.2mm TPU PSM-01_V2.4-350",
    "resolution": "0",
    "seam_gap": "0",
    "skirt_distance": "3",
    "skirt_loops": "1",
    "small_perimeter_speed": "80",
    "small_perimeter_threshold": "5",
    "sparse_infill_acceleration": "10000",
    "sparse_infill_density": "40%",
    "sparse_infill_pattern": "cubic",
    "sparse_infill_speed": "200",
    "support_base_pattern_spacing": "3",
    "support_bottom_interface_spacing": "0",
    "support_bottom_z_distance": "0.15",
    "support_interface_bottom_layers": "0",
    "support_interface_spacing": "0.2",
    "support_interface_top_layers": "3",
    "support_line_width": "0.38",
    "support_speed": "80",
    "support_type": "tree(auto)",
    "top_shell_layers": "5",
    "top_shell_thickness": "1",
    "top_surface_acceleration": "8000",
    "top_surface_speed": "80",
    "travel_acceleration": "45000",
    "travel_speed": "520",
    "tree_support_wall_count": "1",
    "version": "1.4.4.1",
    "wall_loops": "5"
}
